.gitignore
CHANGES.txt
CONTRIBUTORS.txt
COPYRIGHT.txt
LICENSE.txt
README.txt
setup.cfg
setup.py
tox.ini
docs/Makefile
docs/changes.rst
docs/conf.py
docs/index.rst
docs/.static/logo_hi.gif
docs/.static/repoze.css
repoze/__init__.py
repoze.lemonade.egg-info/PKG-INFO
repoze.lemonade.egg-info/SOURCES.txt
repoze.lemonade.egg-info/dependency_links.txt
repoze.lemonade.egg-info/entry_points.txt
repoze.lemonade.egg-info/namespace_packages.txt
repoze.lemonade.egg-info/not-zip-safe
repoze.lemonade.egg-info/requires.txt
repoze.lemonade.egg-info/top_level.txt
repoze/lemonade/__init__.py
repoze/lemonade/content.py
repoze/lemonade/interfaces.py
repoze/lemonade/listitem.py
repoze/lemonade/testing.py
repoze/lemonade/zcml.py
repoze/lemonade/includes/__init__.py
repoze/lemonade/includes/meta.zcml
repoze/lemonade/tests/__init__.py
repoze/lemonade/tests/test_content.py
repoze/lemonade/tests/test_listitem.py
repoze/lemonade/tests/test_testing.py
repoze/lemonade/tests/test_zcml.py
repoze/lemonade/tests/fixtureapp/__init__.py
repoze/lemonade/tests/fixtureapp/configure.zcml
repoze/lemonade/tests/fixtureapp/content.py
repoze/lemonade/tests/fixtureapp/evolve/__init__.py
repoze/lemonade/tests/fixtureapp/evolve/evolve1.py
repoze/lemonade/tests/fixtureapp/evolve/evolve2.py
repoze/lemonade/tests/fixtureapp/evolve/evolve3.py